ocdscardinal-0.0.7.dist-info/METADATA
ocdscardinal-0.0.7.dist-info/WHEEL
ocdscardinal-0.0.7.dist-info/licenses/LICENSE
ocdscardinal/__init__.py
ocdscardinal/ocdscardinal.cpython-312-arm-linux-gnueabihf.so
ocdscardinal-0.0.7.dist-info/RECORD
