Metadata-Version: 2.4
Name: ocdscardinal
Version: 0.0.7
Classifier: License :: OSI Approved :: MIT License
Classifier: Operating System :: OS Independent
Classifier: Programming Language :: Python :: 3.9
Classifier: Programming Language :: Python :: 3.10
Classifier: Programming Language :: Python :: 3.11
Classifier: Programming Language :: Python :: 3.12
Classifier: Programming Language :: Python :: Implementation :: CPython
Classifier: Programming Language :: Rust
License-File: LICENSE
Summary: Measure red flags and procurement indicators using OCDS data
Keywords: cli,json
Home-Page: https://github.com/open-contracting/cardinal-rs
Author: Open Contracting Partnership <data@open-contracting.org>
Author-email: Open Contracting Partnership <data@open-contracting.org>
License: MIT
Project-URL: Homepage, https://github.com/open-contracting/cardinal-rs
